memozo
