Metadata-Version: 1.1
Name: memozo
Version: 0.1.2
Summary: Memotize objects to desk easily
Home-page: https://github.com/sotetsuk/memozo
Author: sotetsuk
Author-email: sotetsu.koyamada@gmail.com
License: MIT
Platform: UNKNOWN
Classifier: Programming Language :: Python :: 3.5
Classifier: License :: OSI Approved :: MIT License
